wdid/__init__.py
wdid/__main__.py
wdid/__version__.py
wdid/bisect.py
wdid/cli.py
wdid/dt_util.py
wdid/entrys.py
wdid/fs_util.py
wdid/plugins/__init__.py
wdid/plugins/impl/__init__.py
wdid/plugins/impl/hamster.py
wdid/plugins/impl/hexchat.py
wdid/plugins/impl/konversation.py
wdid/plugins/impl/local_history.py
wdid/plugins/impl/netbeans.py
wdid/plugins/impl/polari.py
wdid/plugins/impl/zsh.py
wdid-0.0.1a1.dist-info/LICENSE
wdid-0.0.1a1.dist-info/METADATA
wdid-0.0.1a1.dist-info/WHEEL
wdid-0.0.1a1.dist-info/entry_points.txt
wdid-0.0.1a1.dist-info/top_level.txt
wdid-0.0.1a1.dist-info/RECORD
