Metadata-Version: 2.1
Name: wdid
Version: 0.0.1a1
Summary: Recall what you did on a certian day.
Home-page: UNKNOWN
Author: Opal Symes
Author-email: opal@catalyst.net.nz
License: GPLv3+
Platform: UNKNOWN
Classifier: Development Status :: 4 - Beta
Classifier: Environment :: Console
Classifier: Intended Audience :: End Users/Desktop
Classifier: License :: OSI Approved :: GNU General Public License v3 or later (GPLv3+)
Classifier: Natural Language :: English
Classifier: Operating System :: POSIX :: Linux
Classifier: Topic :: Office/Business
Classifier: Topic :: Utilities
Requires-Python: >=3.6
Requires-Dist: pytz
Requires-Dist: click
Requires-Dist: attrs
